nctpy/__init__.py
nctpy/energies.py
nctpy/metrics.py
nctpy/pipelines.py
nctpy/plotting.py
nctpy/utils.py
null_models/__init__.py
null_models/geomsurr.py
tests/__init__.py
tests/make_fixtures.py
tests/test_nctpy.py
nctpy-1.0.1.dist-info/LICENSE
nctpy-1.0.1.dist-info/METADATA
nctpy-1.0.1.dist-info/WHEEL
nctpy-1.0.1.dist-info/top_level.txt
nctpy-1.0.1.dist-info/RECORD
