Metadata-Version: 2.1
Name: nctpy
Version: 1.0.1
Summary: Python implementation of concepts from network control theory
Home-page: https://github.com/LindenParkesLab/nctpy
Author: Linden Parkes, Jason Kim, and Jennifer Stiso
Author-email: lindenparkes@gmail.com, jinsu1@seas.upenn.edu, jeni.stiso@gmail.com
Project-URL: Bug Tracker, https://github.com/LindenParkesLab/nctpy/issues
Classifier: Programming Language :: Python :: 3
Classifier: License :: OSI Approved :: MIT License
Classifier: Operating System :: OS Independent
Requires-Python: >=3.9
License-File: LICENSE
Requires-Dist: numpy
Requires-Dist: scipy
Requires-Dist: tqdm
Requires-Dist: statsmodels
Requires-Dist: seaborn
Requires-Dist: nibabel
Requires-Dist: nilearn
